{
  "resourceType" : "ValueSet",
  "id" : "b4d20c51-6891-44de-bd9a-c245a29d3ec1-179",
  "url" : "http://hl7.org/fhir/comparison/ValueSet/b4d20c51-6891-44de-bd9a-c245a29d3ec1-179",
  "name" : "UnionActTypeRORValueSetAndActTypeRORValueSet",
  "title" : "Union of Valueset type d'acte And Valueset type d'acte",
  "status" : "active",
  "date" : "2024-02-05T22:54:07+00:00",
  "jurisdiction" : [{
    "coding" : [{
      "system" : "urn:iso:std:iso:3166",
      "code" : "FR",
      "display" : "FRANCE"
    }]
  }]
}