{
  "resourceType" : "ValueSet",
  "id" : "9eb3aa45-c170-427f-b28e-50c93751b09d-179",
  "url" : "http://hl7.org/fhir/comparison/ValueSet/9eb3aa45-c170-427f-b28e-50c93751b09d-179",
  "name" : "UnionActTypeRORValueSetAndActTypeRORValueSet",
  "title" : "Union of Valueset type d'acte And Valueset type d'acte",
  "status" : "active",
  "date" : "2024-02-06T00:20:39+00:00",
  "jurisdiction" : [{
    "coding" : [{
      "system" : "urn:iso:std:iso:3166",
      "code" : "FR",
      "display" : "FRANCE"
    }]
  }]
}