{
  "resourceType" : "CodeSystem",
  "id" : "4e6d1b44-564c-4c7f-9057-8e8bc746d826-6",
  "url" : "http://hl7.org/fhir/comparison/CodeSystem/4e6d1b44-564c-4c7f-9057-8e8bc746d826-6",
  "name" : "IntersectionInputTaskRORCodeSystemAndInputTaskRORCodeSystem",
  "title" : "Intersection of null And null",
  "status" : "draft",
  "date" : "2025-07-30T08:56:40+00:00",
  "jurisdiction" : [{
    "coding" : [{
      "system" : "urn:iso:std:iso:3166",
      "code" : "FR",
      "display" : "FRANCE"
    }]
  }],
  "concept" : [{
    "code" : "ruleErrorId",
    "display" : "ruleErrorId",
    "definition" : "Identifiant de la règle à l'origine de l'anomalie"
  },
  {
    "code" : "errorValue",
    "display" : "errorValue",
    "definition" : "donnée erronée"
  },
  {
    "code" : "proposedValue",
    "display" : "proposedValue",
    "definition" : "nouvelle valeur proposée"
  },
  {
    "code" : "pathElementError",
    "display" : "pathElementError",
    "definition" : "élément en erreur dans la ressource"
  },
  {
    "code" : "systemRequester",
    "display" : "systemRequester",
    "definition" : "système déclarant l'anomalie"
  },
  {
    "code" : "identifierRequester",
    "display" : "identifierRequester",
    "definition" : "Identifiant du déclarant de l'anomalie"
  }]
}