{
  "resourceType" : "CodeSystem",
  "id" : "4e6d1b44-564c-4c7f-9057-8e8bc746d826-8",
  "url" : "http://hl7.org/fhir/comparison/CodeSystem/4e6d1b44-564c-4c7f-9057-8e8bc746d826-8",
  "name" : "UnionOutputTaskRORCodeSystemAndOutputTaskRORCodeSystem",
  "title" : "Union of null And null",
  "status" : "draft",
  "date" : "2025-07-30T08:56:40+00:00",
  "jurisdiction" : [{
    "coding" : [{
      "system" : "urn:iso:std:iso:3166",
      "code" : "FR",
      "display" : "FRANCE"
    }]
  }],
  "concept" : [{
    "code" : "newValue",
    "display" : "newValue",
    "definition" : "Nouvelle valeur renseignée"
  },
  {
    "code" : "identifierAnalyst",
    "display" : "identifierAnalyst",
    "definition" : "identifiant du destinataire du traitement de la demande"
  }]
}