{
  "resourceType" : "CodeSystem",
  "id" : "ae22c59c-6e8b-4fc0-bf24-3612bfc50b59-2",
  "url" : "http://hl7.org/fhir/comparison/CodeSystem/ae22c59c-6e8b-4fc0-bf24-3612bfc50b59-2",
  "name" : "UnionActTypeRORCodeSystemAndActTypeRORCodeSystem",
  "title" : "Union of null And null",
  "status" : "draft",
  "date" : "2024-12-03T16:25:33+00:00",
  "jurisdiction" : [{
    "coding" : [{
      "system" : "urn:iso:std:iso:3166",
      "code" : "FR",
      "display" : "FRANCE"
    }]
  }],
  "concept" : [{
    "code" : "specificAct",
    "display" : "specificAct",
    "definition" : "Acte spécifique"
  },
  {
    "code" : "outsideOfficeAct",
    "display" : "outsideOfficeAct",
    "definition" : "Acte hors cabinet"
  }]
}