{
  "resourceType" : "CodeSystem",
  "id" : "adea4394-950b-4a4a-b494-14a6e04fcbdf-2",
  "url" : "http://hl7.org/fhir/comparison/CodeSystem/adea4394-950b-4a4a-b494-14a6e04fcbdf-2",
  "name" : "UnionActTypeRORCodeSystemAndActTypeRORCodeSystem",
  "title" : "Union of null And null",
  "status" : "draft",
  "date" : "2024-12-09T13:17:34+00:00",
  "jurisdiction" : [{
    "coding" : [{
      "system" : "urn:iso:std:iso:3166",
      "code" : "FR",
      "display" : "FRANCE"
    }]
  }],
  "concept" : [{
    "code" : "specificAct",
    "display" : "specificAct",
    "definition" : "Acte spécifique"
  },
  {
    "code" : "outsideOfficeAct",
    "display" : "outsideOfficeAct",
    "definition" : "Acte hors cabinet"
  }]
}