{
  "resourceType" : "ValueSet",
  "id" : "69967dfd-7352-4ce9-a942-fdd325e4f08d-191",
  "url" : "http://hl7.org/fhir/comparison/ValueSet/69967dfd-7352-4ce9-a942-fdd325e4f08d-191",
  "name" : "UnionRORUsageContextTypeVSAndRORUsageContextTypeVS",
  "title" : "Union of Value Set type pour le contexte d'usage de la fiche de saisie And Value Set type pour le contexte d'usage de la fiche de saisie",
  "status" : "draft",
  "date" : "2024-11-28T08:28:35+00:00",
  "jurisdiction" : [{
    "coding" : [{
      "system" : "urn:iso:std:iso:3166",
      "code" : "FR",
      "display" : "FRANCE"
    }]
  }],
  "compose" : {
    "include" : [{
      
    },
    {
      "concept" : [{
        "code" : "EG"
      }]
    },
    {
      "concept" : [{
        "code" : "S"
      }]
    },
    {
      "concept" : [{
        "code" : "P01"
      }]
    }]
  }
}