{
  "resourceType" : "ValueSet",
  "id" : "68ca9f7f-c51c-4ea2-8675-9de25b514888-191",
  "url" : "http://hl7.org/fhir/comparison/ValueSet/68ca9f7f-c51c-4ea2-8675-9de25b514888-191",
  "name" : "UnionRORUsageContextTypeVSAndRORUsageContextTypeVS",
  "title" : "Union of Value Set type pour le contexte d'usage de la fiche de saisie And Value Set type pour le contexte d'usage de la fiche de saisie",
  "status" : "draft",
  "date" : "2025-03-14T08:38:05+00:00",
  "jurisdiction" : [{
    "coding" : [{
      "system" : "urn:iso:std:iso:3166",
      "code" : "FR",
      "display" : "FRANCE"
    }]
  }],
  "compose" : {
    "include" : [{
      
    },
    {
      "concept" : [{
        "code" : "EG"
      }]
    },
    {
      "concept" : [{
        "code" : "S"
      }]
    },
    {
      "concept" : [{
        "code" : "P01"
      }]
    },
    {
      "system" : "https://interop.esante.gouv.fr/ig/fhir/ror/CodeSystem/usage-context-ror-codesystem"
    }]
  }
}